{
  "info": {
    "_postman_id": "12612e1b-9658-4857-96ae-174acdd681b9",
    "name": "produtos1-2026",
    "schema": "https://schema.getpostman.com/json/collection/v2.1.0/collection.json",
    "_exporter_id": "53075870",
    "_collection_link": "https://go.postman.co/collection/53075870-12612e1b-9658-4857-96ae-174acdd681b9?source=collection_link"
  },
  "item": [
    {
      "name": "Categoria",
      "item": [
        {
          "name": "Get all",
          "request": {
            "method": "GET",
            "header": [],
            "url": {
              "raw": "http://{{host}}/categorias",
              "protocol": "http",
              "host": [
                "{{host}}"
              ],
              "path": [
                "categorias"
              ]
            }
          },
          "response": []
        },
        {
          "name": "Get one",
          "request": {
            "method": "GET",
            "header": [],
            "url": {
              "raw": "http://{{host}}/categorias/5",
              "protocol": "http",
              "host": [
                "{{host}}"
              ],
              "path": [
                "categorias",
                "5"
              ]
            }
          },
          "response": []
        }
      ]
    },
    {
      "name": "Produto",
      "item": []
    }
  ]
}